gnome_source_thumbnailer/__init__.py
gnome_source_thumbnailer/resources/application-json-symbolic.svg
gnome_source_thumbnailer/resources/application-x-desktop-symbolic.svg
gnome_source_thumbnailer/resources/application-x-gtk-builder-symbolic.svg
gnome_source_thumbnailer/resources/application-x-php-symbolic.svg
gnome_source_thumbnailer/resources/base.svg
gnome_source_thumbnailer/resources/text-css-symbolic.svg
gnome_source_thumbnailer/resources/text-html-symbolic.svg
gnome_source_thumbnailer/resources/text-markdown-symbolic.svg
gnome_source_thumbnailer/resources/text-plain-symbolic.svg
gnome_source_thumbnailer/resources/text-rust-symbolic.svg
gnome_source_thumbnailer/resources/text-sql-symbolic.svg
gnome_source_thumbnailer/resources/text-x-authors-symbolic.svg
gnome_source_thumbnailer/resources/text-x-changelog-symbolic.svg
gnome_source_thumbnailer/resources/text-x-chdr-symbolic.svg
gnome_source_thumbnailer/resources/text-x-cmake-symbolic.svg
gnome_source_thumbnailer/resources/text-x-copying-symbolic.svg
gnome_source_thumbnailer/resources/text-x-cpp-symbolic.svg
gnome_source_thumbnailer/resources/text-x-csrc-symbolic.svg
gnome_source_thumbnailer/resources/text-x-dbus-service-symbolic.svg
gnome_source_thumbnailer/resources/text-x-generic-symbolic.svg
gnome_source_thumbnailer/resources/text-x-gettext-translation-symbolic.svg
gnome_source_thumbnailer/resources/text-x-gettext-translation-template-symbolic.svg
gnome_source_thumbnailer/resources/text-x-javascript-symbolic.svg
gnome_source_thumbnailer/resources/text-x-log-symbolic.svg
gnome_source_thumbnailer/resources/text-x-makefile-symbolic.svg
gnome_source_thumbnailer/resources/text-x-meson-symbolic.svg
gnome_source_thumbnailer/resources/text-x-patch-symbolic.svg
gnome_source_thumbnailer/resources/text-x-python-symbolic.svg
gnome_source_thumbnailer/resources/text-x-readme-symbolic.svg
gnome_source_thumbnailer/resources/text-x-ruby-symbolic.svg
gnome_source_thumbnailer/resources/text-x-script-symbolic.svg
gnome_source_thumbnailer-0.3.0.dist-info/LICENSE
gnome_source_thumbnailer-0.3.0.dist-info/METADATA
gnome_source_thumbnailer-0.3.0.dist-info/WHEEL
gnome_source_thumbnailer-0.3.0.dist-info/entry_points.txt
gnome_source_thumbnailer-0.3.0.dist-info/top_level.txt
gnome_source_thumbnailer-0.3.0.dist-info/RECORD
