Metadata-Version: 2.1
Name: gnome-source-thumbnailer
Version: 0.3.0
Summary: Thumbnails for your code
Home-page: https://gitlab.gnome.org/ZanderBrown/gnome-source-thumbnailer
Author: Zander Brown
Author-email: zbrown@gnome.org
License: UNKNOWN
Platform: UNKNOWN
Classifier: Programming Language :: Python :: 3
Classifier: License :: OSI Approved :: GNU General Public License v3 (GPLv3)
Classifier: Topic :: Desktop Environment :: Gnome
Classifier: Operating System :: POSIX
Requires-Python: >=3.7
Requires-Dist: pygobject
Requires-Dist: pycairo
